cyra/__init__.py
cyra/core.py
cyra/cyradoc.py
Cyra-1.0.2.dist-info/LICENSE
Cyra-1.0.2.dist-info/METADATA
Cyra-1.0.2.dist-info/WHEEL
Cyra-1.0.2.dist-info/top_level.txt
Cyra-1.0.2.dist-info/RECORD
