Metadata-Version: 2.1
Name: Cyra
Version: 1.0.2
Summary: Cyra is a simple config framework for Python.
Home-page: https://github.com/Theta-Dev/Cyra
Author: ThetaDev
License: MIT License
Platform: UNKNOWN
Classifier: License :: OSI Approved :: MIT License
Classifier: Intended Audience :: Developers
Classifier: Programming Language :: Python :: 2
Classifier: Programming Language :: Python :: 2.7
Classifier: Programming Language :: Python :: 3
Classifier: Programming Language :: Python :: 3.5
Classifier: Programming Language :: Python :: 3.6
Classifier: Programming Language :: Python :: 3.7
Classifier: Programming Language :: Python :: 3.8
Classifier: Programming Language :: Python :: 3.9
Requires-Dist: tomlkit (<1.0.0,>=0.7.0)
